basic_tab_functions/__init__.py
basic_tab_functions/basic_tab_functions.py
basic_tab_functions-0.8.0.dist-info/LICENSE
basic_tab_functions-0.8.0.dist-info/METADATA
basic_tab_functions-0.8.0.dist-info/WHEEL
basic_tab_functions-0.8.0.dist-info/top_level.txt
basic_tab_functions-0.8.0.dist-info/RECORD
