Metadata-Version: 2.1
Name: basic-tab-functions
Version: 0.8.0
Summary: A basic package for reading .txt files
Author-email: Hallgrímur Eggertsson <HallgrimurV@gmail.com>
Project-URL: Homepage, https://github.com/lord_hellgrim/basic_tab_functions
Classifier: Programming Language :: Python :: 3
Classifier: License :: OSI Approved :: MIT License
Classifier: Operating System :: OS Independent
Requires-Python: >=3.7
License-File: LICENSE
